[
    {
        "headline": "Iran accuses US of 'reckless military adventure'",
        "link": "https://bbc.com/watch-live-news/",
        "category": "World",
        "source": "BBC News",
        "timestamp": "2026-05-09T07:48:22.635546"
    },
    {
        "headline": "Trump says Russia and Ukraine to observe three-day ceasefire",
        "link": "https://bbc.com/",
        "category": "World",
        "source": "BBC News",
        "timestamp": "2026-05-09T07:48:22.635564"
    },
    {
        "headline": "US sending charter flight to bring Americans home from hantavirus cruise ship",
        "link": "https://bbc.com/",
        "category": "World",
        "source": "BBC News",
        "timestamp": "2026-05-09T07:48:22.635570"
    },
    {
        "headline": "Return of IS-linked families sparks debate in terror-traumatised Australia",
        "link": "https://bbc.com/sport",
        "category": "World",
        "source": "BBC News",
        "timestamp": "2026-05-09T07:48:22.635574"
    },
    {
        "headline": "Hovering objects and flashing lights: what we learned from UFO documents released by the Pentagon",
        "link": "https://bbc.com/health",
        "category": "World",
        "source": "BBC News",
        "timestamp": "2026-05-09T07:48:22.635578"
    },
    {
        "headline": "Starmer faces growing pressure after Labour suffers heavy election losses",
        "link": "https://bbc.com/watch-live-news/",
        "category": "World",
        "source": "BBC News",
        "timestamp": "2026-05-09T07:48:22.635583"
    },
    {
        "headline": "Analysis: Many Labour MPs blaming the boss for elections body blow",
        "link": "https://bbc.com/news/articles/c99lpn9ze8ro",
        "category": "World",
        "source": "BBC News",
        "timestamp": "2026-05-09T07:48:22.635587"
    },
    {
        "headline": "The race against time to find eagles escaped from Dollywood",
        "link": "https://bbc.com/news/articles/c99lpn9ze8ro",
        "category": "World",
        "source": "BBC News",
        "timestamp": "2026-05-09T07:48:22.635591"
    },
    {
        "headline": "Anger and resignation in Tenerife as hantavirus ship approaches",
        "link": "https://bbc.com/news/articles/c202zn5gg0lo",
        "category": "World",
        "source": "BBC News",
        "timestamp": "2026-05-09T07:48:22.635595"
    },
    {
        "headline": "Hungary's new PM to be sworn in during 'regime change' party",
        "link": "https://bbc.com/news/articles/c4g4r8pm832o",
        "category": "World",
        "source": "BBC News",
        "timestamp": "2026-05-09T07:48:22.635599"
    },
    {
        "headline": "Greece examines mystery naval drone found in Ionian Sea",
        "link": "https://bbc.com/news/articles/cedplx04ew0o",
        "category": "World",
        "source": "BBC News",
        "timestamp": "2026-05-09T07:48:22.635607"
    },
    {
        "headline": "Three dead after volcano erupts on Indonesian island",
        "link": "https://bbc.com/news/articles/c1m2epkey44o",
        "category": "World",
        "source": "BBC News",
        "timestamp": "2026-05-09T07:48:22.635611"
    },
    {
        "headline": "Australian by-election a litmus test for right-wing One Nation Party",
        "link": "https://bbc.com/news/articles/c5yxr7zng6po",
        "category": "World",
        "source": "BBC News",
        "timestamp": "2026-05-09T07:48:22.635615"
    },
    {
        "headline": "William hails Sir David Attenborough's 'remarkable milestone' at 100th birthday concert",
        "link": "https://bbc.com/news/articles/c7597yxey3go",
        "category": "World",
        "source": "BBC News",
        "timestamp": "2026-05-09T07:48:22.635619"
    },
    {
        "headline": "King Charles sends Attenborough a birthday message with help from 'friends'",
        "link": "https://bbc.com/news/articles/c5y0gkg038yo",
        "category": "World",
        "source": "BBC News",
        "timestamp": "2026-05-09T07:48:22.635623"
    },
    {
        "headline": "Ten of Attenborough's best documentaries and where to watch them",
        "link": "https://bbc.com/news/articles/ce3pqvvzgnko",
        "category": "World",
        "source": "BBC News",
        "timestamp": "2026-05-09T07:48:22.635627"
    },
    {
        "headline": "The UFO community has been waiting for answers. Has the Pentagon delivered?",
        "link": "https://bbc.com/news/articles/cx217expnvvo",
        "category": "World",
        "source": "BBC News",
        "timestamp": "2026-05-09T07:48:22.635631"
    },
    {
        "headline": "Anti-work anthems, Boy George and controversial lyrics: A guide to all 35 Eurovision songs",
        "link": "https://bbc.com/news/articles/cp3p418x513o",
        "category": "World",
        "source": "BBC News",
        "timestamp": "2026-05-09T07:48:22.635635"
    },
    {
        "headline": "The companies making billions from the Iran war",
        "link": "https://bbc.com/news/articles/cwy2e4z4npro",
        "category": "World",
        "source": "BBC News",
        "timestamp": "2026-05-09T07:48:22.635639"
    },
    {
        "headline": "The race against time to find eagles escaped from Dollywood",
        "link": "https://bbc.com/news/articles/cq5pwz743j9o",
        "category": "World",
        "source": "BBC News",
        "timestamp": "2026-05-09T07:48:22.635643"
    },
    {
        "headline": "Move over matcha. Hojicha is coming to a cafe near you",
        "link": "https://bbc.com/news/videos/ce3pqvdl1zlo",
        "category": "World",
        "source": "BBC News",
        "timestamp": "2026-05-09T07:48:22.635649"
    },
    {
        "headline": "King Charles sends Attenborough a birthday message with help from 'friends'",
        "link": "https://bbc.com/news/articles/cevevg98125o",
        "category": "World",
        "source": "BBC News",
        "timestamp": "2026-05-09T07:48:22.635653"
    },
    {
        "headline": "Watch: Declassified footage shows 'unidentified anomalous phenomena'",
        "link": "https://bbc.com/news/articles/c707zjg3p42o",
        "category": "World",
        "source": "BBC News",
        "timestamp": "2026-05-09T07:48:22.635657"
    },
    {
        "headline": "Moment former FedEx driver sentenced to death for killing Athena Strand",
        "link": "https://bbc.com/news/articles/c707zjg3p42o",
        "category": "World",
        "source": "BBC News",
        "timestamp": "2026-05-09T07:48:22.635661"
    },
    {
        "headline": "Return of Palestine Marathon attracts thousands of runners",
        "link": "https://bbc.com/news/articles/ce8pmrv2p1mo",
        "category": "World",
        "source": "BBC News",
        "timestamp": "2026-05-09T07:48:22.635667"
    },
    {
        "headline": "Video of man throwing rock at seal in Hawaii sparks anger",
        "link": "https://bbc.com/news/articles/ce8pyyz5e0ro",
        "category": "World",
        "source": "BBC News",
        "timestamp": "2026-05-09T07:48:22.635671"
    },
    {
        "headline": "International cyber attack disrupts swathe of universities and schools",
        "link": "https://bbc.com/news/articles/c7597yxey3go",
        "category": "World",
        "source": "BBC News",
        "timestamp": "2026-05-09T07:48:22.635675"
    },
    {
        "headline": "Missing hiker killed in possible bear attack in Montana",
        "link": "https://bbc.com/news/articles/c232kzgm175o",
        "category": "World",
        "source": "BBC News",
        "timestamp": "2026-05-09T07:48:22.635679"
    },
    {
        "headline": "Are concert livestream tickets the future or a cash-grab?",
        "link": "https://bbc.com/news/videos/ce3pqvdl1zlo",
        "category": "World",
        "source": "BBC News",
        "timestamp": "2026-05-09T07:48:22.635682"
    },
    {
        "headline": "US jet fuel could be used in Europe to ease possible shortages",
        "link": "https://bbc.com/news/videos/c9v3e7vgwxeo",
        "category": "World",
        "source": "BBC News",
        "timestamp": "2026-05-09T07:48:22.635686"
    },
    {
        "headline": "Oasis documentary to show first Gallagher brothers interview in 25 years",
        "link": "https://bbc.com/news/videos/cwy2j93jkv2o",
        "category": "World",
        "source": "BBC News",
        "timestamp": "2026-05-09T07:48:22.635690"
    },
    {
        "headline": "Watch: Return of Palestine Marathon attracts thousands of runners",
        "link": "https://bbc.com/news/videos/cm2p4n000pko",
        "category": "World",
        "source": "BBC News",
        "timestamp": "2026-05-09T07:48:22.635694"
    },
    {
        "headline": "South Africa president faces call to resign after court ruling",
        "link": "https://bbc.com/news/videos/c392jxl22m9o",
        "category": "World",
        "source": "BBC News",
        "timestamp": "2026-05-09T07:48:22.635698"
    },
    {
        "headline": "Hovering objects and flashing lights: what we learned from UFO documents released by the Pentagon",
        "link": "https://bbc.com/news/articles/ce3pq0136eqo",
        "category": "World",
        "source": "BBC News",
        "timestamp": "2026-05-09T07:48:22.635702"
    },
    {
        "headline": "Iran accuses US of 'reckless military adventure'",
        "link": "https://bbc.com/news/articles/ce3pq0136eqo",
        "category": "World",
        "source": "BBC News",
        "timestamp": "2026-05-09T07:48:22.635708"
    },
    {
        "headline": "Greece examines mystery naval drone found in Ionian Sea",
        "link": "https://bbc.com/news/articles/c1m2egmnxg3o",
        "category": "World",
        "source": "BBC News",
        "timestamp": "2026-05-09T07:48:22.635712"
    },
    {
        "headline": "Return of IS-linked families sparks debate in terror-traumatised Australia",
        "link": "https://bbc.com/news/articles/c1j74x9pe0eo",
        "category": "World",
        "source": "BBC News",
        "timestamp": "2026-05-09T07:48:22.635716"
    },
    {
        "headline": "Anger and resignation in Tenerife as hantavirus ship approaches",
        "link": "https://bbc.com/news/articles/cp8pk2m4nlxo",
        "category": "World",
        "source": "BBC News",
        "timestamp": "2026-05-09T07:48:22.635720"
    },
    {
        "headline": "Missing hiker killed in possible bear attack in Montana",
        "link": "https://bbc.com/news/articles/c0q2n5e20xjo",
        "category": "World",
        "source": "BBC News",
        "timestamp": "2026-05-09T07:48:22.635724"
    },
    {
        "headline": "William hails Sir David Attenborough's 'remarkable milestone' at 100th birthday concert",
        "link": "https://bbc.com/news/videos/cm2p4n000pko",
        "category": "World",
        "source": "BBC News",
        "timestamp": "2026-05-09T07:48:22.635727"
    },
    {
        "headline": "The UFO community has been waiting for answers. Has the Pentagon delivered?",
        "link": "https://bbc.com/news/articles/cy4287vpvl7o",
        "category": "World",
        "source": "BBC News",
        "timestamp": "2026-05-09T07:48:22.635733"
    },
    {
        "headline": "The race against time to find eagles escaped from Dollywood",
        "link": "https://bbc.com/news/articles/c1m2epkey44o",
        "category": "World",
        "source": "BBC News",
        "timestamp": "2026-05-09T07:48:22.635737"
    },
    {
        "headline": "Many Labour MPs are blaming the boss for elections body blow",
        "link": "https://bbc.com/news/articles/c99lpn9ze8ro",
        "category": "World",
        "source": "BBC News",
        "timestamp": "2026-05-09T07:48:22.635741"
    },
    {
        "headline": "Fernandes: The trophies, the assist record and his future",
        "link": "https://bbc.com/news/articles/cx217expnvvo",
        "category": "World",
        "source": "BBC News",
        "timestamp": "2026-05-09T07:48:22.635745"
    },
    {
        "headline": "Arteta rallies Arsenal for huge Premier League weekend",
        "link": "https://bbc.com/news/articles/cedplx04ew0o",
        "category": "World",
        "source": "BBC News",
        "timestamp": "2026-05-09T07:48:22.635749"
    },
    {
        "headline": "Tight-lipped Dubois weighs in at career-heavy 18st",
        "link": "https://bbc.com/news/articles/c5y0gkg038yo",
        "category": "World",
        "source": "BBC News",
        "timestamp": "2026-05-09T07:48:22.635752"
    },
    {
        "headline": "'Good business' for PGA Tour if LIV players return - McIlroy",
        "link": "https://bbc.com/news/articles/c1m2egmnxg3o",
        "category": "World",
        "source": "BBC News",
        "timestamp": "2026-05-09T07:48:22.635756"
    },
    {
        "headline": "From cricket to 'bosh' queen - England prop Muir",
        "link": "https://bbc.com/news/articles/cq5pwz743j9o",
        "category": "World",
        "source": "BBC News",
        "timestamp": "2026-05-09T07:48:22.635760"
    },
    {
        "headline": "Real Madrid in crisis - inside the conflict and chaos at the Bernabeu",
        "link": "https://bbc.com/news/articles/c707zjg3p42o",
        "category": "World",
        "source": "BBC News",
        "timestamp": "2026-05-09T07:48:22.635764"
    },
    {
        "headline": "Spurs and Knicks win on road in Conference semis",
        "link": "https://bbc.com/news/articles/c7597yxey3go",
        "category": "World",
        "source": "BBC News",
        "timestamp": "2026-05-09T07:48:22.635768"
    },
    {
        "headline": "Four Takeaways From the U.K. Elections",
        "link": "https://nytimes.com/2026/05/08/world/europe/uk-elections-local-takeaways.html",
        "category": "World",
        "source": "New York Times",
        "timestamp": "2026-05-09T07:48:22.982690"
    },
    {
        "headline": "How China\u2019s Leader Lost Faith in His Generals",
        "link": "https://nytimes.com/2026/05/09/world/asia/china-military-generals.html",
        "category": "World",
        "source": "New York Times",
        "timestamp": "2026-05-09T07:48:22.982704"
    },
    {
        "headline": "Mette Frederiksen Fails to Form Governing Coalition in Denmark",
        "link": "https://nytimes.com/2026/05/08/world/europe/denmark-frederiksen-right-wing-government.html",
        "category": "World",
        "source": "New York Times",
        "timestamp": "2026-05-09T07:48:22.982709"
    },
    {
        "headline": "Before Hantavirus Outbreak, This Cruise Attracted \u2018a Different Type of Traveler\u2019",
        "link": "https://nytimes.com/2026/05/08/world/hantavirus-mv-hondius-cruise.html",
        "category": "World",
        "source": "New York Times",
        "timestamp": "2026-05-09T07:48:22.982715"
    }
]