[
    {
        "headline": "US continues search for missing crew member from downed jet as Iran offers reward for their capture",
        "link": "https://bbc.com/watch-live-news/",
        "category": "World",
        "source": "BBC News",
        "timestamp": "2026-04-04T06:53:12.926530"
    },
    {
        "headline": "How elite US teams tackle combat rescue missions",
        "link": "https://bbc.com/",
        "category": "World",
        "source": "BBC News",
        "timestamp": "2026-04-04T06:53:12.926553"
    },
    {
        "headline": "Burkina Faso must 'forget' about democracy, military leader says",
        "link": "https://bbc.com/",
        "category": "World",
        "source": "BBC News",
        "timestamp": "2026-04-04T06:53:12.926559"
    },
    {
        "headline": "Unanswered questions remain after death of Australia's most wanted fugitive",
        "link": "https://bbc.com/sport",
        "category": "World",
        "source": "BBC News",
        "timestamp": "2026-04-04T06:53:12.926565"
    },
    {
        "headline": "Russia chose 'Easter escalation' over ceasefire, says Zelensky",
        "link": "https://bbc.com/health",
        "category": "World",
        "source": "BBC News",
        "timestamp": "2026-04-04T06:53:12.926571"
    },
    {
        "headline": "Artemis II crew now halfway to Moon as they take 'spectacular' image of Earth",
        "link": "https://bbc.com/watch-live-news/",
        "category": "World",
        "source": "BBC News",
        "timestamp": "2026-04-04T06:53:12.926577"
    },
    {
        "headline": "After 16 years in power, can Viktor Orban finally be unseated?",
        "link": "https://bbc.com/news/articles/c0le43jw8e9o",
        "category": "World",
        "source": "BBC News",
        "timestamp": "2026-04-04T06:53:12.926582"
    },
    {
        "headline": "Faced with new energy shock, Europe asks if reviving nuclear is the answer",
        "link": "https://bbc.com/news/articles/cly0zp1xgz3o",
        "category": "World",
        "source": "BBC News",
        "timestamp": "2026-04-04T06:53:12.926588"
    },
    {
        "headline": "Italy's famed Uffizi admits cyber-attack but denies security breach",
        "link": "https://bbc.com/news/articles/cg7358zzz0no",
        "category": "World",
        "source": "BBC News",
        "timestamp": "2026-04-04T06:53:12.926606"
    },
    {
        "headline": "Football rally in Peru leaves one dead and dozens injured",
        "link": "https://bbc.com/news/articles/cew70wjvv9do",
        "category": "World",
        "source": "BBC News",
        "timestamp": "2026-04-04T06:53:12.926612"
    },
    {
        "headline": "Rapper Gucci Mane kidnapped and robbed by fellow artist, prosecutors say",
        "link": "https://bbc.com/news/articles/ce8jzr423p9o",
        "category": "World",
        "source": "BBC News",
        "timestamp": "2026-04-04T06:53:12.926618"
    },
    {
        "headline": "France's Muslim gathering ban overturned by courts",
        "link": "https://bbc.com/news/articles/czd7y1n3jyjo",
        "category": "World",
        "source": "BBC News",
        "timestamp": "2026-04-04T06:53:12.926623"
    },
    {
        "headline": "No positive drug tests during Winter Olympics, for first time in 28 years",
        "link": "https://bbc.com/news/articles/c4g8k8vq8gno",
        "category": "World",
        "source": "BBC News",
        "timestamp": "2026-04-04T06:53:12.926628"
    },
    {
        "headline": "Experts dispute US account of deadly Iran sports hall strike in Lamerd",
        "link": "https://bbc.com/news/articles/cy51wzeq6g5o",
        "category": "World",
        "source": "BBC News",
        "timestamp": "2026-04-04T06:53:12.926633"
    },
    {
        "headline": "International law experts allege violations in Iran war",
        "link": "https://bbc.com/news/articles/ckgxyn3ljgjo",
        "category": "World",
        "source": "BBC News",
        "timestamp": "2026-04-04T06:53:12.926639"
    },
    {
        "headline": "When will the Iran war end? Tracing the Trump administration's timelines",
        "link": "https://bbc.com/news/articles/c937kezj03vo",
        "category": "World",
        "source": "BBC News",
        "timestamp": "2026-04-04T06:53:12.926644"
    },
    {
        "headline": "'This has got me worried': Iranians fear what comes next after US strike on Karaj bridge",
        "link": "https://bbc.com/news/articles/cwyjekvwww0o",
        "category": "World",
        "source": "BBC News",
        "timestamp": "2026-04-04T06:53:12.926650"
    },
    {
        "headline": "French-owned ship passes through Strait of Hormuz",
        "link": "https://bbc.com/sport/articles/ce8jzpj6nyko",
        "category": "World",
        "source": "BBC News",
        "timestamp": "2026-04-04T06:53:12.926655"
    },
    {
        "headline": "Watch: Artemis II's journey so far as it leaves Earth orbit... in 85 seconds",
        "link": "https://bbc.com/news/articles/c4gx8e1x5j3o",
        "category": "World",
        "source": "BBC News",
        "timestamp": "2026-04-04T06:53:12.926661"
    },
    {
        "headline": "Power-washing, pool-cleaning and mowing: Why millions are playing games about mundane jobs",
        "link": "https://bbc.com/news/articles/cy91x2n29nlo",
        "category": "World",
        "source": "BBC News",
        "timestamp": "2026-04-04T06:53:12.926666"
    },
    {
        "headline": "What not to say to a friend who is struggling to conceive",
        "link": "https://bbc.com/news/articles/c4g4e6z9960o",
        "category": "World",
        "source": "BBC News",
        "timestamp": "2026-04-04T06:53:12.926671"
    },
    {
        "headline": "What to know about Acting Attorney General Todd Blanche",
        "link": "https://bbc.com/news/articles/cp86mrj40e2o",
        "category": "World",
        "source": "BBC News",
        "timestamp": "2026-04-04T06:53:12.926677"
    },
    {
        "headline": "How Bombay went from a fort city to a bustling metropolis",
        "link": "https://bbc.com/news/articles/cjd8275jrrko",
        "category": "World",
        "source": "BBC News",
        "timestamp": "2026-04-04T06:53:12.926684"
    },
    {
        "headline": "'We want a voice in our land' - the people evicted to build Nigeria's capital",
        "link": "https://bbc.com/news/videos/cpqxn8zx8ydo",
        "category": "World",
        "source": "BBC News",
        "timestamp": "2026-04-04T06:53:12.926691"
    },
    {
        "headline": "How Canada's largest gun control effort in decades is missing the mark",
        "link": "https://bbc.com/news/videos/cpqxn8zx8ydo",
        "category": "World",
        "source": "BBC News",
        "timestamp": "2026-04-04T06:53:12.926696"
    },
    {
        "headline": "Watch: Artemis II's journey so far as it leaves Earth orbit... in 85 seconds",
        "link": "https://bbc.com/news/articles/cj60r2kdnw1o",
        "category": "World",
        "source": "BBC News",
        "timestamp": "2026-04-04T06:53:12.926702"
    },
    {
        "headline": "Marshmallows fall from the sky at annual Michigan Easter event",
        "link": "https://bbc.com/news/articles/cvgk8yxxkvpo",
        "category": "World",
        "source": "BBC News",
        "timestamp": "2026-04-04T06:53:12.926707"
    },
    {
        "headline": "Video appears to show US plane and search and rescue helicopters over southern Iran",
        "link": "https://bbc.com/news/videos/c747w0zejzmo",
        "category": "World",
        "source": "BBC News",
        "timestamp": "2026-04-04T06:53:12.926712"
    },
    {
        "headline": "Why isn't Artemis II landing on the Moon?",
        "link": "https://bbc.com/news/articles/cj60k3x879ro",
        "category": "World",
        "source": "BBC News",
        "timestamp": "2026-04-04T06:53:12.926717"
    },
    {
        "headline": "What to know about Acting Attorney General Todd Blanche",
        "link": "https://bbc.com/news/articles/clyggr00x5vo",
        "category": "World",
        "source": "BBC News",
        "timestamp": "2026-04-04T06:53:12.926722"
    },
    {
        "headline": "Trump removes US Attorney General Pam Bondi",
        "link": "https://bbc.com/news/articles/cvg09dq4x5qo",
        "category": "World",
        "source": "BBC News",
        "timestamp": "2026-04-04T06:53:12.926728"
    },
    {
        "headline": "Cuba begins releasing more than 2,000 prisoners as US pressure mounts",
        "link": "https://bbc.com/news/videos/cpqxn8zx8ydo",
        "category": "World",
        "source": "BBC News",
        "timestamp": "2026-04-04T06:53:12.926732"
    },
    {
        "headline": "Fears cost of water and beer to soar as India's scorching summer hits",
        "link": "https://bbc.com/news/videos/cvglpewvx15o",
        "category": "World",
        "source": "BBC News",
        "timestamp": "2026-04-04T06:53:12.926739"
    },
    {
        "headline": "US deports eight people 'of African origin' to Uganda",
        "link": "https://bbc.com/news/videos/cly68eg7px6o",
        "category": "World",
        "source": "BBC News",
        "timestamp": "2026-04-04T06:53:12.926744"
    },
    {
        "headline": "US jobs surge unexpectedly in March despite Iran war",
        "link": "https://bbc.com/news/videos/c3w344wyxg5o",
        "category": "World",
        "source": "BBC News",
        "timestamp": "2026-04-04T06:53:12.926749"
    },
    {
        "headline": "Italy part company with manager after failing to qualify for World Cup",
        "link": "https://bbc.com/news/videos/c747w0zejzmo",
        "category": "World",
        "source": "BBC News",
        "timestamp": "2026-04-04T06:53:12.926754"
    },
    {
        "headline": "Trump seeks $1.5tn for defence alongside domestic spending cuts",
        "link": "https://bbc.com/news/articles/ce843ge47z4o",
        "category": "World",
        "source": "BBC News",
        "timestamp": "2026-04-04T06:53:12.926759"
    },
    {
        "headline": "Artemis II crew now halfway to Moon as they take 'spectacular' image of Earth",
        "link": "https://bbc.com/news/articles/ce843ge47z4o",
        "category": "World",
        "source": "BBC News",
        "timestamp": "2026-04-04T06:53:12.926763"
    },
    {
        "headline": "Rescue team in Iran face 'harrowing and dangerous' search for US crew member",
        "link": "https://bbc.com/news/articles/cwy3r3w4zl8o",
        "category": "World",
        "source": "BBC News",
        "timestamp": "2026-04-04T06:53:12.926768"
    },
    {
        "headline": "After 16 years in power, can Viktor Orban finally be unseated?",
        "link": "https://bbc.com/news/articles/c5ywqky5dd7o",
        "category": "World",
        "source": "BBC News",
        "timestamp": "2026-04-04T06:53:12.926774"
    },
    {
        "headline": "How Canada's largest gun control effort in decades is missing the mark",
        "link": "https://bbc.com/news/articles/c8ej43z8yw4o",
        "category": "World",
        "source": "BBC News",
        "timestamp": "2026-04-04T06:53:12.926779"
    },
    {
        "headline": "Unanswered questions remain after death of Australia's most wanted fugitive",
        "link": "https://bbc.com/news/articles/crk165g4vv3o",
        "category": "World",
        "source": "BBC News",
        "timestamp": "2026-04-04T06:53:12.926783"
    },
    {
        "headline": "Faced with new energy shock, Europe asks if reviving nuclear is the answer",
        "link": "https://bbc.com/sport/football/articles/cevk0mn93ejo",
        "category": "World",
        "source": "BBC News",
        "timestamp": "2026-04-04T06:53:12.926788"
    },
    {
        "headline": "Burkina Faso must 'forget' about democracy, military leader says",
        "link": "https://bbc.com/news/articles/crr1q4kjvn2o",
        "category": "World",
        "source": "BBC News",
        "timestamp": "2026-04-04T06:53:12.926793"
    },
    {
        "headline": "Experts dispute US account of deadly Iran sports hall strike in Lamerd",
        "link": "https://bbc.com/news/articles/ce8jzr423p9o",
        "category": "World",
        "source": "BBC News",
        "timestamp": "2026-04-04T06:53:12.926798"
    },
    {
        "headline": "Cuba begins releasing more than 2,000 prisoners as US pressure mounts",
        "link": "https://bbc.com/news/articles/c0le43jw8e9o",
        "category": "World",
        "source": "BBC News",
        "timestamp": "2026-04-04T06:53:12.926803"
    },
    {
        "headline": "Rapper Gucci Mane kidnapped and robbed by fellow artist, prosecutors say",
        "link": "https://bbc.com/news/articles/czd7y1n3jyjo",
        "category": "World",
        "source": "BBC News",
        "timestamp": "2026-04-04T06:53:12.926807"
    },
    {
        "headline": "After more than 14 years at Atletico Madrid, what next for Simeone?",
        "link": "https://bbc.com/news/articles/cvg09dq4x5qo",
        "category": "World",
        "source": "BBC News",
        "timestamp": "2026-04-04T06:53:12.926812"
    },
    {
        "headline": "Guardiola wants Rodri to stay but says unhappy stars can go",
        "link": "https://bbc.com/news/articles/cg7358zzz0no",
        "category": "World",
        "source": "BBC News",
        "timestamp": "2026-04-04T06:53:12.926816"
    },
    {
        "headline": "Arteta defends Arsenal's international withdrawals",
        "link": "https://bbc.com/news/articles/c4g8k8vq8gno",
        "category": "World",
        "source": "BBC News",
        "timestamp": "2026-04-04T06:53:12.926820"
    },
    {
        "headline": "Isak could make injury return against Man City",
        "link": "https://bbc.com/news/articles/cly0zp1xgz3o",
        "category": "World",
        "source": "BBC News",
        "timestamp": "2026-04-04T06:53:12.926825"
    },
    {
        "headline": "Football rally in Peru leaves one dead and dozens injured",
        "link": "https://bbc.com/news/articles/c4gx8e1x5j3o",
        "category": "World",
        "source": "BBC News",
        "timestamp": "2026-04-04T06:53:12.926829"
    },
    {
        "headline": "The thorny issues facing F1 over racing, qualifying and safety",
        "link": "https://bbc.com/news/articles/cwy3r3w4zl8o",
        "category": "World",
        "source": "BBC News",
        "timestamp": "2026-04-04T06:53:12.926834"
    },
    {
        "headline": "Chelsea's Fernandez dropped after 'crossing a line'",
        "link": "https://bbc.com/news/articles/c937kezj03vo",
        "category": "World",
        "source": "BBC News",
        "timestamp": "2026-04-04T06:53:12.926838"
    },
    {
        "headline": "Hegseth Says U.S. Troops Are Fighting for Jesus. The Pope Disagrees.",
        "link": "https://nytimes.com/2026/04/03/world/middleeast/pope-iran-war.html",
        "category": "World",
        "source": "New York Times",
        "timestamp": "2026-04-04T06:53:13.191878"
    },
    {
        "headline": "How Israel Is Taking Control of Southern Lebanon",
        "link": "https://nytimes.com/interactive/2026/04/03/world/middleeast/israel-military-southern-lebanon-hezbollah.html",
        "category": "World",
        "source": "New York Times",
        "timestamp": "2026-04-04T06:53:13.191892"
    },
    {
        "headline": "In Syria, Kidnappings of Women and Girls Fuel a Minority Group\u2019s Fears",
        "link": "https://nytimes.com/2026/04/03/world/middleeast/syria-kidnapping-alawite-woman-girls.html",
        "category": "World",
        "source": "New York Times",
        "timestamp": "2026-04-04T06:53:13.191897"
    },
    {
        "headline": "At War With Iran Again, Some Israelis Fear Conflict Is Becoming Routine",
        "link": "https://nytimes.com/2026/04/03/world/middleeast/israel-war-mood.html",
        "category": "World",
        "source": "New York Times",
        "timestamp": "2026-04-04T06:53:13.191902"
    }
]