[
    {
        "headline": "Trump says Syria 'not our fight'. Staying out may not be so easy",
        "link": "https://bbc.com/",
        "category": "World",
        "source": "BBC News",
        "timestamp": "2024-12-13T06:19:16.099976"
    },
    {
        "headline": "After 50 years of Assad cruelty, Syrians search for dead loved ones - and closure",
        "link": "https://bbc.com/watch-live-news/",
        "category": "World",
        "source": "BBC News",
        "timestamp": "2024-12-13T06:19:16.099995"
    },
    {
        "headline": "Jude Law gets a star on Hollywood Walk of Fame",
        "link": "https://bbc.com/",
        "category": "World",
        "source": "BBC News",
        "timestamp": "2024-12-13T06:19:16.100000"
    },
    {
        "headline": "Steven Bartlett sharing harmful health misinformation in Diary of CEO podcast",
        "link": "https://bbc.com/sport",
        "category": "World",
        "source": "BBC News",
        "timestamp": "2024-12-13T06:19:16.100005"
    },
    {
        "headline": "The Indian teen who became the world's youngest chess champion",
        "link": "https://bbc.com/video",
        "category": "World",
        "source": "BBC News",
        "timestamp": "2024-12-13T06:19:16.100009"
    },
    {
        "headline": "After 50 years of Assad cruelty, Syrians search for dead loved ones - and closure",
        "link": "https://bbc.com/news/articles/c0j1z5ylgjjo",
        "category": "World",
        "source": "BBC News",
        "timestamp": "2024-12-13T06:19:16.100014"
    },
    {
        "headline": "Bloody siege ends Myanmar army control of western border",
        "link": "https://bbc.com/news/articles/cq5lwq911dwo",
        "category": "World",
        "source": "BBC News",
        "timestamp": "2024-12-13T06:19:16.100018"
    },
    {
        "headline": "Harshita Brella 'told family her husband will kill her'",
        "link": "https://bbc.com/news/videos/cx2v6jxy7g1o",
        "category": "World",
        "source": "BBC News",
        "timestamp": "2024-12-13T06:19:16.100022"
    },
    {
        "headline": "Biden issues 39 presidential pardons and commutes 1,500 sentences",
        "link": "https://bbc.com/news/articles/c4gpz163vg2o",
        "category": "World",
        "source": "BBC News",
        "timestamp": "2024-12-13T06:19:16.100026"
    },
    {
        "headline": "Jude Law gets a star on Hollywood Walk of Fame",
        "link": "https://bbc.com/news/articles/c23vn7x4012o",
        "category": "World",
        "source": "BBC News",
        "timestamp": "2024-12-13T06:19:16.100031"
    },
    {
        "headline": "Trump rings bell on record stock market - but will it last?",
        "link": "https://bbc.com/news/articles/cq5lwq911dwo",
        "category": "World",
        "source": "BBC News",
        "timestamp": "2024-12-13T06:19:16.100035"
    },
    {
        "headline": "Country singer sentenced after throwing chair off Nashville bar roof",
        "link": "https://bbc.com/news/articles/ckg324den6po",
        "category": "World",
        "source": "BBC News",
        "timestamp": "2024-12-13T06:19:16.100039"
    },
    {
        "headline": "Net closing in on South Korea's president as MPs get death threats over impeachment vote",
        "link": "https://bbc.com/news/articles/cy897z272qjo",
        "category": "World",
        "source": "BBC News",
        "timestamp": "2024-12-13T06:19:16.100046"
    },
    {
        "headline": "Three men accuse Diddy of rape and sexual assault in new lawsuits",
        "link": "https://bbc.com/news/articles/c30nq7r0v2mo",
        "category": "World",
        "source": "BBC News",
        "timestamp": "2024-12-13T06:19:16.100050"
    },
    {
        "headline": "Nato must switch to a wartime mindset, warns secretary general",
        "link": "https://bbc.com/news/videos/cx2v6jxy7g1o",
        "category": "World",
        "source": "BBC News",
        "timestamp": "2024-12-13T06:19:16.100056"
    },
    {
        "headline": "'I wish he'd lived to see new Syria' - Crowds bury anti-Assad activist",
        "link": "https://bbc.com/news/articles/clyn8yjw11go",
        "category": "World",
        "source": "BBC News",
        "timestamp": "2024-12-13T06:19:16.100060"
    },
    {
        "headline": "Jeremy Bowen: Assad's palace, once a symbol of power, now an empty shell",
        "link": "https://bbc.com/news/articles/cj90e41e7wlo",
        "category": "World",
        "source": "BBC News",
        "timestamp": "2024-12-13T06:19:16.100066"
    },
    {
        "headline": "Inside Aleppo, the first city to fall to Syrian rebels",
        "link": "https://bbc.com/news/articles/cvg7pv278ezo",
        "category": "World",
        "source": "BBC News",
        "timestamp": "2024-12-13T06:19:16.100071"
    },
    {
        "headline": "Syria rebel leader vows to shut down notorious Assad prisons",
        "link": "https://bbc.com/news/articles/c1mre8mpemxo",
        "category": "World",
        "source": "BBC News",
        "timestamp": "2024-12-13T06:19:16.100075"
    },
    {
        "headline": "Israel seizing on Syria chaos to strike military assets",
        "link": "https://bbc.com/news/articles/cly41x7eg71o",
        "category": "World",
        "source": "BBC News",
        "timestamp": "2024-12-13T06:19:16.100079"
    },
    {
        "headline": "Hate people fidgeting? Join the misokinesia club",
        "link": "https://bbc.com/news/articles/c89xgke2x7lo",
        "category": "World",
        "source": "BBC News",
        "timestamp": "2024-12-13T06:19:16.100083"
    },
    {
        "headline": "Weekly quiz: Which film bagged the most Golden Globe nominations?",
        "link": "https://bbc.com/news/videos/c2exwm28p3lo",
        "category": "World",
        "source": "BBC News",
        "timestamp": "2024-12-13T06:19:16.100087"
    },
    {
        "headline": "Could airships be the next cruise ships?",
        "link": "https://bbc.com/news/articles/c3wexlp91n4o",
        "category": "World",
        "source": "BBC News",
        "timestamp": "2024-12-13T06:19:16.100091"
    },
    {
        "headline": "Is India's economic boom fading?",
        "link": "https://bbc.com/news/articles/c047579lzklo",
        "category": "World",
        "source": "BBC News",
        "timestamp": "2024-12-13T06:19:16.100095"
    },
    {
        "headline": "'Thankless job' - why trainee Kenyan doctors are taking their own lives",
        "link": "https://bbc.com/news/articles/cdx921zreweo",
        "category": "World",
        "source": "BBC News",
        "timestamp": "2024-12-13T06:19:16.100099"
    },
    {
        "headline": "Weekly quiz: Which film bagged the most Golden Globe nominations?",
        "link": "https://bbc.com/news/articles/c8ewl757d2ko",
        "category": "World",
        "source": "BBC News",
        "timestamp": "2024-12-13T06:19:16.100103"
    },
    {
        "headline": "Humans may not have survived without Neanderthals",
        "link": "https://bbc.com/news/articles/cx2n0xjrrjpo",
        "category": "World",
        "source": "BBC News",
        "timestamp": "2024-12-13T06:19:16.100107"
    },
    {
        "headline": "Where next for Iran now that its 'Axis of Resistance' is shattered",
        "link": "https://bbc.com/news/videos/cdd6ee91gz4o",
        "category": "World",
        "source": "BBC News",
        "timestamp": "2024-12-13T06:19:16.100111"
    },
    {
        "headline": "Could airships be the next cruise ships?",
        "link": "https://bbc.com/news/articles/cre7z8w080qo",
        "category": "World",
        "source": "BBC News",
        "timestamp": "2024-12-13T06:19:16.100116"
    },
    {
        "headline": "Jeremy Bowen: Assad's palace, once a symbol of power, now an empty shell",
        "link": "https://bbc.com/news/articles/cx2n0xjrrjpo",
        "category": "World",
        "source": "BBC News",
        "timestamp": "2024-12-13T06:19:16.100120"
    },
    {
        "headline": "Watch: Man trying to escape police gets stuck in chimney",
        "link": "https://bbc.com/news/articles/cwydgyy8120o",
        "category": "World",
        "source": "BBC News",
        "timestamp": "2024-12-13T06:19:16.100124"
    },
    {
        "headline": "Jude Law gets a star on Hollywood Walk of Fame",
        "link": "https://bbc.com/news/articles/c05pmmzp63zo",
        "category": "World",
        "source": "BBC News",
        "timestamp": "2024-12-13T06:19:16.100128"
    },
    {
        "headline": "BBC sees crowd surge over rumoured execution of Assad henchman",
        "link": "https://bbc.com/news/videos/c2exwm28p3lo",
        "category": "World",
        "source": "BBC News",
        "timestamp": "2024-12-13T06:19:16.100132"
    },
    {
        "headline": "Moment rubbish truck explodes in a Chicago suburb",
        "link": "https://bbc.com/news/videos/cj495k8jl2xo",
        "category": "World",
        "source": "BBC News",
        "timestamp": "2024-12-13T06:19:16.100136"
    },
    {
        "headline": "Moment rubbish truck explodes in a Chicago suburb",
        "link": "https://bbc.com/news/videos/cx2v6jxy7g1o",
        "category": "World",
        "source": "BBC News",
        "timestamp": "2024-12-13T06:19:16.100140"
    },
    {
        "headline": "Trump ally Kari Lake tapped to lead Voice of America",
        "link": "https://bbc.com/news/videos/c3e3vjk4e7vo",
        "category": "World",
        "source": "BBC News",
        "timestamp": "2024-12-13T06:19:16.100144"
    },
    {
        "headline": "Moment of relief as Romania and Bulgaria join EU border-free zone",
        "link": "https://bbc.com/news/videos/c708zjlep9go",
        "category": "World",
        "source": "BBC News",
        "timestamp": "2024-12-13T06:19:16.100150"
    },
    {
        "headline": "Rape inquiry linked by Swedish media to Mbapp\u00e9 closed",
        "link": "https://bbc.com/news/videos/c708zjlep9go",
        "category": "World",
        "source": "BBC News",
        "timestamp": "2024-12-13T06:19:16.100154"
    },
    {
        "headline": "Former F1 team boss Jordan reveals cancer diagnosis",
        "link": "https://bbc.com/news/articles/cq627z3493po",
        "category": "World",
        "source": "BBC News",
        "timestamp": "2024-12-13T06:19:16.100159"
    },
    {
        "headline": "Trump ally Kari Lake tapped to lead Voice of America",
        "link": "https://bbc.com/news/articles/cn4xjj4xde3o",
        "category": "World",
        "source": "BBC News",
        "timestamp": "2024-12-13T06:19:16.100163"
    },
    {
        "headline": "King Charles visits Christmas market and tours Apple with Tim Cook",
        "link": "https://bbc.com/news/articles/cgkxgd4rkexo",
        "category": "World",
        "source": "BBC News",
        "timestamp": "2024-12-13T06:19:16.100167"
    },
    {
        "headline": "Israeli strikes kill 12 guarding Gaza aid lorries, medics say",
        "link": "https://bbc.com/sport/formula1/articles/cn8502y285eo",
        "category": "World",
        "source": "BBC News",
        "timestamp": "2024-12-13T06:19:16.100171"
    },
    {
        "headline": "Moment of relief as Romania and Bulgaria join EU border-free zone",
        "link": "https://bbc.com/news/articles/cq627z3493po",
        "category": "World",
        "source": "BBC News",
        "timestamp": "2024-12-13T06:19:16.100175"
    },
    {
        "headline": "Harshita Brella 'told family her husband will kill her'",
        "link": "https://bbc.com/news/articles/c623x2p7kzwo",
        "category": "World",
        "source": "BBC News",
        "timestamp": "2024-12-13T06:19:16.100179"
    },
    {
        "headline": "Trump says Syria 'not our fight'. Staying out may not be so easy",
        "link": "https://bbc.com/news/articles/crk0x64ll8jo",
        "category": "World",
        "source": "BBC News",
        "timestamp": "2024-12-13T06:19:16.100183"
    },
    {
        "headline": "Biden issues 39 presidential pardons and commutes 1,500 sentences",
        "link": "https://bbc.com/news/articles/cn4xjj4xde3o",
        "category": "World",
        "source": "BBC News",
        "timestamp": "2024-12-13T06:19:16.100187"
    },
    {
        "headline": "Bloody siege ends Myanmar army control of western border",
        "link": "https://bbc.com/news/articles/cy897z272qjo",
        "category": "World",
        "source": "BBC News",
        "timestamp": "2024-12-13T06:19:16.100191"
    },
    {
        "headline": "Three men accuse Diddy of rape and sexual assault in new lawsuits",
        "link": "https://bbc.com/news/articles/c0j1z5ylgjjo",
        "category": "World",
        "source": "BBC News",
        "timestamp": "2024-12-13T06:19:16.100195"
    },
    {
        "headline": "Nato must switch to a wartime mindset, warns secretary general",
        "link": "https://bbc.com/news/articles/c30nq7r0v2mo",
        "category": "World",
        "source": "BBC News",
        "timestamp": "2024-12-13T06:19:16.100199"
    },
    {
        "headline": "Humans may not have survived without Neanderthals",
        "link": "https://bbc.com/news/articles/ckg324den6po",
        "category": "World",
        "source": "BBC News",
        "timestamp": "2024-12-13T06:19:16.100204"
    },
    {
        "headline": "The Indian teen who became the world's youngest chess champion",
        "link": "https://bbc.com/news/articles/c1mre8mpemxo",
        "category": "World",
        "source": "BBC News",
        "timestamp": "2024-12-13T06:19:16.100208"
    },
    {
        "headline": "Where next for Iran now that its 'Axis of Resistance' is shattered",
        "link": "https://bbc.com/news/articles/cly41x7eg71o",
        "category": "World",
        "source": "BBC News",
        "timestamp": "2024-12-13T06:19:16.100212"
    },
    {
        "headline": "After 50 years of Assad cruelty, Syrians search for dead loved ones - and closure",
        "link": "https://bbc.com/news/articles/cwydgyy8120o",
        "category": "World",
        "source": "BBC News",
        "timestamp": "2024-12-13T06:19:16.100216"
    },
    {
        "headline": "'Spurs' lost tourists ransacked by revived Rangers'",
        "link": "https://bbc.com/news/articles/c23vn7x4012o",
        "category": "World",
        "source": "BBC News",
        "timestamp": "2024-12-13T06:19:16.100222"
    },
    {
        "headline": "Is Man Utd keeper Onana part of problem or solution for Amorim?",
        "link": "https://bbc.com/news/articles/c05pmmzp63zo",
        "category": "World",
        "source": "BBC News",
        "timestamp": "2024-12-13T06:19:16.100226"
    },
    {
        "headline": "Greenwood injury mars Man City Champions League win",
        "link": "https://bbc.com/news/articles/cq5lwq911dwo",
        "category": "World",
        "source": "BBC News",
        "timestamp": "2024-12-13T06:19:16.100230"
    },
    {
        "headline": "Body found in search for former England rugby player Voyce",
        "link": "https://bbc.com/sport/football/articles/c9dpj4e347lo",
        "category": "World",
        "source": "BBC News",
        "timestamp": "2024-12-13T06:19:16.100234"
    },
    {
        "headline": "Stokes admits putting 'too much emphasis' on Ashes",
        "link": "https://bbc.com/sport/football/articles/cy4pvwgv88qo",
        "category": "World",
        "source": "BBC News",
        "timestamp": "2024-12-13T06:19:16.100238"
    },
    {
        "headline": "Is Man Utd keeper Onana part of problem or solution for Amorim?",
        "link": "https://bbc.com/news/articles/c1kej2m3dvvo",
        "category": "World",
        "source": "BBC News",
        "timestamp": "2024-12-13T06:19:16.100244"
    },
    {
        "headline": "'It's not acceptable, I said that to him' - Postecoglou on Werner display",
        "link": "https://bbc.com/sport/cricket/articles/c17d5en7k49o",
        "category": "World",
        "source": "BBC News",
        "timestamp": "2024-12-13T06:19:16.100250"
    },
    {
        "headline": "'He's been watching Suarez' - the Chelsea fringe stars shining in Europe",
        "link": "https://bbc.com/sport/football/articles/cy4pvwgv88qo",
        "category": "World",
        "source": "BBC News",
        "timestamp": "2024-12-13T06:19:16.100254"
    },
    {
        "headline": "Greenwood injury mars Man City Champions League win",
        "link": "https://bbc.com/sport/football/articles/c1elgq4pz4no",
        "category": "World",
        "source": "BBC News",
        "timestamp": "2024-12-13T06:19:16.100258"
    },
    {
        "headline": "Biden Commutes the Sentences of 1,500 Americans, a Record for One Day",
        "link": "https://nytimes.com/2024/12/12/us/politics/biden-pardons-commutes-1500.html",
        "category": "World",
        "source": "New York Times",
        "timestamp": "2024-12-13T06:19:16.226426"
    },
    {
        "headline": "How America Created the Enemy It Feared Most",
        "link": "https://nytimes.com/2024/12/12/world/europe/afghanistan-allies-enemies-nuristan-taliban.html",
        "category": "World",
        "source": "New York Times",
        "timestamp": "2024-12-13T06:19:16.226437"
    },
    {
        "headline": "In Milei\u2019s Argentina, Economic Albatross Is Tamed but Life Is Much Harder",
        "link": "https://nytimes.com/2024/12/12/world/americas/argentina-president-milei-inflation-economy.html",
        "category": "World",
        "source": "New York Times",
        "timestamp": "2024-12-13T06:19:16.226442"
    },
    {
        "headline": "His Daughter Went Missing in 1999. He Couldn\u2019t Let It Go.",
        "link": "https://nytimes.com/2024/12/12/world/asia/south-korea-missing-person-fliers.html",
        "category": "World",
        "source": "New York Times",
        "timestamp": "2024-12-13T06:19:16.226447"
    }
]